statutils/__init__.py
statutils/multi_comparison.py
statutils-0.1.0.dist-info/LICENSE
statutils-0.1.0.dist-info/METADATA
statutils-0.1.0.dist-info/WHEEL
statutils-0.1.0.dist-info/top_level.txt
statutils-0.1.0.dist-info/RECORD
